<?xml version="1.0" encoding="ISO-8859-1"?>
<!-- edited with XMLSPY v2004 rel. 2 U (http://www.xmlspy.com) by lcollins (Firaxis Games) -->
<!-- Sid Meier's Civilization 4 -->
<!-- Copyright Firaxis Games 2005 -->
<!-- -->
<!-- Game Text - New -->
<Civ4GameText xmlns="http://www.firaxis.com">
	<TEXT>
		<Tag>TXT_KEY_NO_ACTION_HAS_HOME_CITY</Tag>
		<English>[COLOR_UNIT_TEXT]Current Home Settlement: %s1_city.[COLOR_REVERT]</English>
		<French>[COLOR_UNIT_TEXT]Current Home Settlement: %s1_city.[COLOR_REVERT]</French>
		<German>[COLOR_UNIT_TEXT]Current Home Settlement: %s1_city.[COLOR_REVERT]</German>
		<Italian>[COLOR_UNIT_TEXT]Current Home Settlement: %s1_city.[COLOR_REVERT]</Italian>
		<Spanish>[COLOR_UNIT_TEXT]Current Home Settlement: %s1_city.[COLOR_REVERT]</Spanish>
	</TEXT>
	<TEXT>
		<Tag>TXT_KEY_SELECT_HOME_CITY</Tag>
		<English>Select a Home Settlement for this Unit</English>
		<French>Select a Home Settlement for this Unit</French>
		<German>Select a Home Settlement for this Unit</German>
		<Italian>Select a Home Settlement for this Unit</Italian>
		<Spanish>Select a Home Settlement for this Unit</Spanish>
	</TEXT>
	<TEXT>
		<Tag>TXT_KEY_SELECT_HOME_CITY_NAME</Tag>
		<English>%s1_city (%d2_population)</English>
		<French>%s1_city (%d2_population)</French>
		<German>%s1_city (%d2_population)</German>
		<Italian>%s1_city (%d2_population)</Italian>
		<Spanish>%s1_city (%d2_population)</Spanish>
	</TEXT>
	<TEXT>
		<Tag>TXT_KEY_CLEAR_HOME_CITY</Tag>
		<English>Clear home settlement</English>
		<French>Clear home settlement</French>
		<German>Clear home settlement</German>
		<Italian>Clear home settlement</Italian>
		<Spanish>Clear home settlement</Spanish>
	</TEXT>
	<TEXT>
		<Tag>TXT_KEY_RETURN_HOME_UNLOAD</Tag>
		<English>Return Home and Unload</English>
		<French>Return Home and Unload</French>
		<German>Return Home and Unload</German>
		<Italian>Return Home and Unload</Italian>
		<Spanish>Return Home and Unload</Spanish>
	</TEXT>
	<TEXT>
		<Tag>TXT_KEY_AUTOMATE_IMMIGRATION</Tag>
		<English>Immigrating</English>
		<French>Immigrating</French>
		<German>Immigrating</German>
		<Italian>Immigrating</Italian>
		<Spanish>Immigrating</Spanish>
	</TEXT>
	<TEXT>
		<Tag>TXT_KEY_RETURN_HOME_UNLOAD_HELP</Tag>
		<English>Return to home settlement and unload cargo if able.</English>
		<French>Return to home settlement and unload cargo if able.</French>
		<German>Return to home settlement and unload cargo if able.</German>
		<Italian>Return to home settlement and unload cargo if able.</Italian>
		<Spanish>Return to home settlement and unload cargo if able.</Spanish>
	</TEXT>
	<TEXT>
		<Tag>TXT_KEY_ASSIGN_HOME_CITY</Tag>
		<English>Assign Home Settlement</English>
		<French>Assign Home Settlement</French>
		<German>Assign Home Settlement</German>
		<Italian>Assign Home Settlement</Italian>
		<Spanish>Assign Home Settlement</Spanish>
	</TEXT>
	<TEXT>
		<Tag>TXT_KEY_ASSIGN_HOME_CITY_HELP</Tag>
		<English>Select a Home Settlement. Units can then return here to unload if able.</English>
		<French>Assign Home Settlement</French>
		<German>Assign Home Settlement</German>
		<Italian>Assign Home Settlement</Italian>
		<Spanish>Assign Home Settlement</Spanish>
	</TEXT>
</Civ4GameText>
